optax_swag/__init__.py
optax_swag/sample.py
optax_swag/state.py
optax_swag/transform.py
optax_swag-0.1.0.dist-info/LICENSE
optax_swag-0.1.0.dist-info/METADATA
optax_swag-0.1.0.dist-info/WHEEL
optax_swag-0.1.0.dist-info/top_level.txt
optax_swag-0.1.0.dist-info/RECORD
