Metadata-Version: 2.1
Name: optax-swag
Version: 0.1.0
Summary: Stochastic Weight Averaging for Optax
License: Apache License 2.0
Classifier: Intended Audience :: Developers
Classifier: Intended Audience :: Science/Research
Classifier: License :: OSI Approved :: Apache Software License
Classifier: Topic :: Scientific/Engineering :: Artificial Intelligence
License-File: LICENSE
Requires-Dist: optax
